README.md
setup.py
yandexwebmaster/__init__.py
yandexwebmaster/core.py
yandexwebmaster.egg-info/PKG-INFO
yandexwebmaster.egg-info/SOURCES.txt
yandexwebmaster.egg-info/dependency_links.txt
yandexwebmaster.egg-info/requires.txt
yandexwebmaster.egg-info/top_level.txt