Metadata-Version: 1.0
Name: yandexwebmaster
Version: 0.0.2
Summary: YandexWebmaster API
Home-page: UNKNOWN
Author: Danillab
Author-email: danillab@yandex.ru
License: MIT
Keywords: yandex webmaster
Platform: UNKNOWN
